pecha_org_tools/__init__.py
pecha_org_tools/config.py
pecha_org_tools/extract.py
pecha_org_tools/translation.py
pecha_org_tools/utils.py
pecha_org_tools-0.0.8.dist-info/LICENSE
pecha_org_tools-0.0.8.dist-info/METADATA
pecha_org_tools-0.0.8.dist-info/WHEEL
pecha_org_tools-0.0.8.dist-info/RECORD
