Metadata-Version: 2.1
Name: pecha-org-tools
Version: 0.0.8
Summary: A package to help with data preparation for pecha.org
Author: Tsundue
Author-email: tsundue@esukhia.org
Requires-Python: >=3.9,<4.0
Classifier: License :: OSI Approved :: MIT License
Classifier: Operating System :: OS Independent
Classifier: Programming Language :: Python :: 3
Classifier: Programming Language :: Python :: 3.9
Classifier: Programming Language :: Python :: 3.10
Classifier: Programming Language :: Python :: 3.11
Classifier: Programming Language :: Python :: 3.12
Requires-Dist: anthropic (==0.40.0)
Requires-Dist: openpyxl (>=3.1.5)
Requires-Dist: urllib3 (>=2.2.3)
Project-URL: Bug Tracker, https://github.com/OpenPecha/openpecha-project-template/issues
Project-URL: Homepage, https://github.com/OpenPecha/openpecha-project-template
